project/script1.py
pritom_package-1.0.0.dist-info/LICENSE
pritom_package-1.0.0.dist-info/METADATA
pritom_package-1.0.0.dist-info/WHEEL
pritom_package-1.0.0.dist-info/entry_points.txt
pritom_package-1.0.0.dist-info/top_level.txt
pritom_package-1.0.0.dist-info/RECORD
