Metadata-Version: 2.1
Name: pritom-package
Version: 1.0.0
Summary: My first python package
Home-page: UNKNOWN
Author: Pritom Hazarika
License: MIT
Platform: UNKNOWN
Classifier: License :: OSI Approved :: MIT License
Classifier: Programming Language :: Python :: 3
Classifier: Programming Language :: Python :: 3.7
Requires-Dist: requests
